belousov_zhabotinsky/__init__.py
belousov_zhabotinsky/main.py
belousov_zhabotinsky-0.6.1.dist-info/LICENSE
belousov_zhabotinsky-0.6.1.dist-info/METADATA
belousov_zhabotinsky-0.6.1.dist-info/WHEEL
belousov_zhabotinsky-0.6.1.dist-info/entry_points.txt
belousov_zhabotinsky-0.6.1.dist-info/top_level.txt
belousov_zhabotinsky-0.6.1.dist-info/RECORD
