Metadata-Version: 2.1
Name: belousov-zhabotinsky
Version: 0.6.1
Summary: Simulation of the Belousov-Zhabotinski reaction using ASCII art
Home-page: https://github.com/neumann-mlucas/belousov-zhabotinsky
Author: Lucas Stefan Minuzzi Neumann
Author-email: neumannmlucas@gmail.com
License: UNKNOWN
Platform: UNKNOWN
Classifier: Programming Language :: Python :: 3
Classifier: License :: OSI Approved :: GNU General Public License v3 (GPLv3)
Classifier: Operating System :: OS Independent
Requires-Python: >=3
Requires-Dist: numpy
Requires-Dist: scipy
